MANIFEST.in
README.md
setup.py
app_init_cli.egg-info/PKG-INFO
app_init_cli.egg-info/SOURCES.txt
app_init_cli.egg-info/dependency_links.txt
app_init_cli.egg-info/entry_points.txt
app_init_cli.egg-info/not-zip-safe
app_init_cli.egg-info/requires.txt
app_init_cli.egg-info/top_level.txt
webplatform_cli/Docker.py
webplatform_cli/Handler.py
webplatform_cli/Parser.py
webplatform_cli/__init__.py
webplatform_cli/cli.py
webplatform_cli/containers/__init__.py
webplatform_cli/containers/main.py
webplatform_cli/data/README.md
webplatform_cli/docker/actions/jobs/build.sh
webplatform_cli/docker/actions/jobs/entry.sh
webplatform_cli/docker/actions/jobs/start.py
webplatform_cli/docker/actions/mongodb/entry.sh
webplatform_cli/docker/actions/nginx/build.sh
webplatform_cli/docker/actions/nginx/entry.sh
webplatform_cli/docker/actions/nginx/restart.sh
webplatform_cli/docker/actions/nginx/setup.sh
webplatform_cli/docker/actions/nginx/start.sh
webplatform_cli/docker/actions/nginx/stop.sh
webplatform_cli/docker/actions/nginx/update.sh
webplatform_cli/docker/actions/webpack/entry.sh
webplatform_cli/docker/base/Dockerfile
webplatform_cli/docker/base/entry.sh
webplatform_cli/docker/base/mongodb-org.repo
webplatform_cli/docker/base/platform-requirements.txt
webplatform_cli/docker/base/requirements.txt
webplatform_cli/docker/mongodb/conf.yaml
webplatform_cli/docker/nginx/nginx-cold.conf
webplatform_cli/docker/nginx/nginx.conf
webplatform_cli/lib/__init__.py
webplatform_cli/lib/config.py
webplatform_cli/lib/db.py
webplatform_cli/settings/auth.json
webplatform_cli/settings/mongodb.json
webplatform_cli/settings/nginx.json
webplatform_cli/settings/variables.json
webplatform_cli/settings/webpack.json
webplatform_cli/tasks/__init__.py
webplatform_cli/tasks/build.py
webplatform_cli/tasks/create.py