Metadata-Version: 1.2
Name: app-init-cli
Version: 1.0.0
Summary: CLI used for a webplatform
Home-page: https://github.com/app-init/cli
Author: Matthew Owens
Author-email: mowens@redhat.com
License: MIT
Platform: UNKNOWN
Classifier: Programming Language :: Python :: 3
Classifier: License :: OSI Approved :: MIT License
Classifier: Operating System :: OS Independent
Requires-Python: >=3
